hca/__init__.py
hca/cli.py
hca/config.py
hca/default_config.json
hca/version.py
hca/auth/__init__.py
hca/auth/cli.py
hca/dss/__init__.py
hca/dss/cli.py
hca/dss/error.py
hca/dss/infra.py
hca/dss/upload_to_cloud.py
hca/dss/util/__init__.py
hca/packages/__init__.py
hca/upload/__init__.py
hca/upload/exceptions.py
hca/upload/upload_area.py
hca/upload/upload_area_uri.py
hca/upload/upload_config.py
hca/upload/upload_service.py
hca/upload/cli/__init__.py
hca/upload/cli/common.py
hca/upload/cli/creds_command.py
hca/upload/cli/forget_command.py
hca/upload/cli/generate_status_report_command.py
hca/upload/cli/list_area_command.py
hca/upload/cli/list_areas_command.py
hca/upload/cli/list_file_status_command.py
hca/upload/cli/select_command.py
hca/upload/cli/upload_command.py
hca/upload/lib/__init__.py
hca/upload/lib/api_client.py
hca/upload/lib/client_side_checksum_handler.py
hca/upload/lib/credentials_manager.py
hca/upload/lib/s3_agent.py
hca/upload/lib/upload_submission_state.py
hca/util/__init__.py
hca/util/_docs.py
hca/util/compat.py
hca/util/exceptions.py
hca/util/fs_helper.py
hca/util/pool.py
hca/util/tsv.py
test/integration/__init__.py
test/integration/auth/__init__.py
test/integration/auth/test_auth_api.py
test/integration/dss/__init__.py
test/integration/dss/test_dss_api.py
test/integration/dss/test_dss_api_retry.py
test/integration/dss/test_dss_cli.py
test/integration/upload/__init__.py
test/integration/upload/test_upload_area.py
test/integration/upload/test_upload_config.py
test/integration/upload/test_upload_service.py
test/integration/upload/cli/__init__.py
test/integration/upload/cli/test_creds.py
test/integration/upload/cli/test_file_status.py
test/integration/upload/cli/test_forget.py
test/integration/upload/cli/test_generate_status_report.py
test/integration/upload/cli/test_list_area.py
test/integration/upload/cli/test_list_areas.py
test/integration/upload/cli/test_select.py
test/integration/upload/cli/test_upload.py
test/integration/upload/lib/__init__.py
hca-7.0.1.dist-info/LICENSE
hca-7.0.1.dist-info/METADATA
hca-7.0.1.dist-info/WHEEL
hca-7.0.1.dist-info/entry_points.txt
hca-7.0.1.dist-info/top_level.txt
hca-7.0.1.dist-info/RECORD
