Metadata-Version: 2.1
Name: hca
Version: 7.0.1
Summary: Human Cell Atlas Data Storage System Command Line Interface
Home-page: https://github.com/HumanCellAtlas/dcp-cli
Author: Human Cell Atlas contributors
Author-email: akislyuk@chanzuckerberg.com
License: Apache Software License
Platform: MacOS X
Platform: Posix
Classifier: Intended Audience :: Developers
Classifier: License :: OSI Approved :: Apache Software License
Classifier: Operating System :: MacOS :: MacOS X
Classifier: Operating System :: POSIX
Classifier: Programming Language :: Python
Classifier: Programming Language :: Python :: 3.3
Classifier: Programming Language :: Python :: 3.4
Classifier: Programming Language :: Python :: 3.5
Classifier: Programming Language :: Python :: 3.6
Classifier: Programming Language :: Python :: 3.7
Classifier: Topic :: Software Development :: Libraries :: Python Modules
Requires-Dist: argcomplete (<2,>=1.9.3)
Requires-Dist: atomicwrites (<2,>=1.3.0)
Requires-Dist: boto3 (<2,>=1.9.86)
Requires-Dist: botocore (<2,>=1.12.208)
Requires-Dist: commonmark (<1,>=0.9.0)
Requires-Dist: cryptography (<3,>=2.6.1)
Requires-Dist: dcplib (<3,>=2.0.2)
Requires-Dist: docutils (<0.16)
Requires-Dist: google-auth (<2,>=1.3.0)
Requires-Dist: google-auth-oauthlib (<2,>=0.4.1)
Requires-Dist: Jinja2 (<3,>=2.10)
Requires-Dist: jsonpointer (<2,>=1.10)
Requires-Dist: jsonschema (<3,>=2.6)
Requires-Dist: puremagic (<1.5,>=1.4)
Requires-Dist: PyJWT (<2,>=1.6.4)
Requires-Dist: requests (<3,>=2.20.0)
Requires-Dist: tenacity (<5.1,>=5.0.2)
Requires-Dist: tqdm (<5,>=4.33.0)
Requires-Dist: tweak (<2,>=1.0.3)
Requires-Dist: typing (<4,>=3.6.2) ; python_version < "3.5"
Requires-Dist: scandir (<2,>=1.9.0) ; python_version < "3.5"
